<?xml version="1.0" encoding="UTF-8"?>
<layout>
    <font filename="/var/pdfgeneration/fonts/GildaDisplay-Regular.ttf"/>
    <field id="today" xpos="110" ypos="150"/>

    <field id="pname" xpos="135" ypos="190" />

    <field id="sex_Female" xpos="105" ypos="208" font-size="10"/>
    <field id="sex_Male" xpos="159" ypos="208" font-size="10"/>

    <field id="phone" xpos="477" ypos="208" font-size="7"/>
    
    <field id="DOB_MDY" xpos="320" ypos="207" />
    
    <field id="address" xpos="143" ypos="226" font-size='7' />
    <field id="city" xpos="391" ypos="226" font-size='7' />
    <field id="zip" xpos="540" ypos="226" font-size='7' />

    <field id="language_english" xpos="151" ypos="243"/>    
    <field id="language_spanish" xpos="214" ypos="243"/>
    <field id="language_vietnamese" xpos="278" ypos="243"/>        
    <field id="language_farsi" xpos="359" ypos="243"/>

    <field id="language_other" xpos="404" ypos="243"/>
    <field id="language_other_text" xpos="478" ypos="243"/>

    <field id="education_request_weight" xpos="56" ypos="317"/>
    <field id="education_request_diabetes" xpos="209" ypos="317"/>
    <field id="education_request_other" xpos="289" ypos="317"/>
    <field id="education_request_text" xpos="415" ypos="317"/>
            
    <field id="to-learn" xpos="260" ypos="335"/>
    
    
    <field id="Physician" xpos="219" ypos="360" font-size="10"/>
    
    <field id="height" xpos="555" ypos="540"/>
    <field id="weight" xpos="423" ypos="540"/>
    <field id="bmi" xpos="315" ypos="540"/>

    <field id="bmi_pct" xpos="550" ypos="588"/>
    <field id="stature_date" xpos="198" ypos="540"/>

    <field id="lead" xpos="240" ypos="235"/>
    
    
    <field id="provider-name" xpos="162" ypos="381"/>
    <field id="provider-address" xpos="162" ypos="398"/>
    <field id="provider-city-zip" xpos="162" ypos="415"/>
    <field id="contact-name" xpos="162" ypos="434"/>

        
    <field id="provider-id" xpos="478" ypos="381"/>
    <field id="provider-phone" xpos="478" ypos="398"/>
    <field id="provider-fax" xpos="478" ypos="415"/>
    <field id="contact-phone" xpos="478" ypos="434"/>

    <field id="signature-date" xpos="530" ypos="665"/>

    <field id="coptp-primary_278.00" xpos="56" ypos="587" font-size="8"/>
    <field id="coptp-primary_278.01" xpos="56" ypos="598" font-size="8"/>
    <field id="coptp-primary_278.02" xpos="56" ypos="610" font-size="8"/>
    
    <field id="coptp-secondary_V85.53" xpos="347" ypos="587" font-size="8"/>
    <field id="coptp-secondary_V85.54" xpos="347" ypos="598" font-size="8"/>
\    
    
</layout>
